README.md
setup.cfg
setup.py
Topsis_IshaanTakkar_101803025/topsis.py
Topsis_IshaanTakkar_101803025.egg-info/PKG-INFO
Topsis_IshaanTakkar_101803025.egg-info/SOURCES.txt
Topsis_IshaanTakkar_101803025.egg-info/dependency_links.txt
Topsis_IshaanTakkar_101803025.egg-info/entry_points.txt
Topsis_IshaanTakkar_101803025.egg-info/requires.txt
Topsis_IshaanTakkar_101803025.egg-info/top_level.txt