Metadata-Version: 2.1
Name: Topsis-IshaanTakkar-101803025
Version: 1.0.7
Summary: A package -> Calculates Topsis Score and Rank them accordingly
Home-page: https://github.com/takkar99/Topsis_IshaanTakkar_101803025
Author: Ishaan Takkar
Author-email: ishaantakkar@gmail.com
License: MIT
Platform: UNKNOWN
Classifier: Programming Language :: Python :: 3
Classifier: License :: OSI Approved :: MIT License
Classifier: Operating System :: OS Independent
